loomhr/__init__.py
loomhr/py.typed
loomhr/rest_utils.py
loomhr/specialist.py
loomhr_python_sdk-1.0.0.dist-info/LICENSE.txt
loomhr_python_sdk-1.0.0.dist-info/METADATA
loomhr_python_sdk-1.0.0.dist-info/WHEEL
loomhr_python_sdk-1.0.0.dist-info/top_level.txt
loomhr_python_sdk-1.0.0.dist-info/RECORD
