Metadata-Version: 2.1
Name: loomhr-python-sdk
Version: 1.0.0
Summary: SDK library for LoomHR specialist developers
Home-page: https://loomhr.ai/build/api_reference
Author: LoomHR
Author-email: spec-support@loomhr.ai
Keywords: LoomHR python
Classifier: Programming Language :: Python :: 3.11
Classifier: License :: OSI Approved :: MIT License
Classifier: Operating System :: OS Independent
Requires-Python: >=3.10
License-File: LICENSE.txt
Requires-Dist: locked-dict >=2023.10.22
